tvolib/__init__.py
tvolib/legacy/models/__init__.py
tvolib/legacy/models/magnetopause_model.py
tvolib/legacy/numeric/__init__.py
tvolib/legacy/numeric/curlometer.py
tvolib/legacy/numeric/interpolate.py
tvolib/legacy/numeric/moving.py
tvolib/legacy/numeric/timing.py
tvolib/logging.py
tvolib/matplotlib_utils/__init__.py
tvolib/matplotlib_utils/_draw.py
tvolib/matplotlib_utils/_format.py
tvolib/matplotlib_utils/_setup.py
tvolib/matplotlib_utils/data/tvolib.mplstyle
tvolib-0.5.3.dist-info/LICENSE.md
tvolib-0.5.3.dist-info/METADATA
tvolib-0.5.3.dist-info/WHEEL
tvolib-0.5.3.dist-info/RECORD
